bsn/__init__.py
bsn/bsn.py
bsn-0.0.2.dist-info/LICENSE.txt
bsn-0.0.2.dist-info/METADATA
bsn-0.0.2.dist-info/WHEEL
bsn-0.0.2.dist-info/top_level.txt
bsn-0.0.2.dist-info/RECORD
