Metadata-Version: 2.1
Name: bsn
Version: 0.0.2
Summary: This package can be used to test whether a number is a bsn (Burger Service Number, Dutch Social Security Number), but it can also generate the numbers
Home-page: https://github.com/marcenthoven/bsn
Author: Marc Enthoven
Author-email: marc_enthoven@hotmail.com
License: UNKNOWN
Platform: UNKNOWN
Classifier: Programming Language :: Python :: 3
Classifier: License :: OSI Approved :: MIT License
Classifier: Operating System :: OS Independent
Requires-Dist: numpy
